ts3audiobot_api/__init__.py
ts3audiobot_api/commands.py
ts3audiobot_api/ts3audiobot.py
ts3audiobot_api/ts3commandcaller.py
ts3audiobot_api-0.0.3.9.dist-info/LICENSE
ts3audiobot_api-0.0.3.9.dist-info/METADATA
ts3audiobot_api-0.0.3.9.dist-info/WHEEL
ts3audiobot_api-0.0.3.9.dist-info/top_level.txt
ts3audiobot_api-0.0.3.9.dist-info/RECORD
