Metadata-Version: 2.1
Name: ts3audiobot-api
Version: 0.0.3.9
Summary: API Wrapper for TS3AudioBot
Home-page: https://github.com/EverHype-Systems/ts3audiobot-wrapper
Author: EverHype Systems
Author-email: abajrami@everhype-systems.eu
License: UNKNOWN
Platform: UNKNOWN
Classifier: Programming Language :: Python :: 3
Classifier: License :: OSI Approved :: GNU General Public License v3 or later (GPLv3+)
Classifier: Operating System :: OS Independent
Requires-Python: >=3.6
